{"id":"4e3dc7f6-3122-4d1e-9d4b-5cba7a2959b6","timestamp":1759742044140,"matcher":{"static":{},"wildcard":{},"dynamic":{}},"prerendered":["/","/policy","/delivery","/rezka","/return","/contacts","/rospis","/cart","/checkout","/search","/partnerships","/personal-data","/sale","/category/plitka","/category/klei","/category/keramogranit","/category/stupeni","/category/klinker","/category/vanny","/category/unitazy","/category/santexnika","/category/mozaika","/category/installiacii","/category/dusevye-kabiny","/category/smesiteli","/category/zatirka"]}